featureuitls/__init__.py
featureuitls/featureUtils.py
featureuitls/main.py
featureuitls/oneFuntion.py
dw_feature_tool-1.0.7.dist-info/LICENSE
dw_feature_tool-1.0.7.dist-info/METADATA
dw_feature_tool-1.0.7.dist-info/WHEEL
dw_feature_tool-1.0.7.dist-info/top_level.txt
dw_feature_tool-1.0.7.dist-info/RECORD
